LICENSE
MANIFEST.in
README.rst
requirements.txt
setup.py
cenpy/__init__.py
cenpy/explorer.py
cenpy/geoparser.py
cenpy/products.py
cenpy/remote.py
cenpy/stfipstable.csv
cenpy/tiger.py
cenpy/tools.py
cenpy.egg-info/PKG-INFO
cenpy.egg-info/SOURCES.txt
cenpy.egg-info/dependency_links.txt
cenpy.egg-info/not-zip-safe
cenpy.egg-info/requires.txt
cenpy.egg-info/top_level.txt