Metadata-Version: 1.2
Name: cenpy
Version: 1.0.0.post3
Summary: Explore and download data from Census APIs
Home-page: https://github.com/cenpy-devs/cenpy
Author: Levi John Wolf
Author-email: levi.john.wolf@gmail.com
License: 3-Clause BSD
Platform: UNKNOWN
Requires-Python: >=3.5
